src/__init__.py
src/data/__init__.py
src/data/annotation.py
src/data/segment.py
src/data/segment_backend/__init__.py
src/data/segment_backend/segment_backend.py
src/data/segment_backend/simple_backend.py
src/file_readers/__init__.py
src/file_readers/csv_reader.py
src/file_readers/file_reader.py
honeyannote-0.3.0.dist-info/METADATA
honeyannote-0.3.0.dist-info/WHEEL
honeyannote-0.3.0.dist-info/licenses/LICENSE
honeyannote-0.3.0.dist-info/RECORD
