Metadata-Version: 2.4
Name: honeyannote
Version: 0.3.0
Summary: A library for dealing with segmented data
License: MIT
License-File: LICENSE
Author: Lawrence Borst
Author-email: laurens.s.borst@gmail.com
Requires-Python: >=3.13
Classifier: License :: OSI Approved :: MIT License
Classifier: Programming Language :: Python :: 3
Classifier: Programming Language :: Python :: 3.13
Classifier: Programming Language :: Python :: 3.14
